odoo_image_changelog/__init__.py
odoo_image_changelog/github_helpers.py
odoo_image_changelog/main.py
odoo_image_changelog-0.3.2.dist-info/METADATA
odoo_image_changelog-0.3.2.dist-info/WHEEL
odoo_image_changelog-0.3.2.dist-info/entry_points.txt
odoo_image_changelog-0.3.2.dist-info/top_level.txt
odoo_image_changelog-0.3.2.dist-info/RECORD
